setup.py
zmqpy/__init__.py
zmqpy/_cffi.py
zmqpy/_ctypes.py
zmqpy/constants.py
zmqpy/error.py
zmqpy/zmqpy.py
zmqpy.egg-info/PKG-INFO
zmqpy.egg-info/SOURCES.txt
zmqpy.egg-info/dependency_links.txt
zmqpy.egg-info/requires.txt
zmqpy.egg-info/top_level.txt
zmqpy/eventloop/__init__.py
zmqpy/eventloop/ioloop.py
zmqpy/eventloop/stack_context.py
zmqpy/eventloop/zmqstream.py
zmqpy/tests/__init__.py
zmqpy/tests/test_cffi_backend.py
zmqpy/tests/test_zmqpy.py
zmqpy/tests/test_zmqstream.py
zmqpy/tests/pyzmq_tests/__init__.py
zmqpy/tests/pyzmq_tests/test_context.py
zmqpy/tests/pyzmq_tests/test_ioloop.py
zmqpy/tests/pyzmq_tests/test_pair.py
zmqpy/tests/pyzmq_tests/test_poller.py
zmqpy/tests/pyzmq_tests/test_pubsub.py
zmqpy/utils/__init__.py
zmqpy/utils/jsonapi.py
zmqpy/utils/strtypes.py