Metadata-Version: 1.0
Name: zmqpy
Version: 0.3.3.2
Summary: Python cffi-based ZeroMQ bindings
Home-page: https://github.com/felipecruz/zmqpy
Author: Felipe Cruz
Author-email: felipecruz@loogica.net
License: UNKNOWN
Platform: UNKNOWN
